[
    { "uid": "102309705322", "nickname": "皮卡丘开箱" },
    { "uid": "97071917893", "nickname": "锦鲤开箱" },
    { "uid": "97310601926", "nickname": "南山无颜祖" },
    { "uid": "103930813179", "nickname": "神奇开箱组" },
    { "uid": "95439502967", "nickname": "可乐优品" },
    { "uid": "103654529592", "nickname": "蒙面科技" },
    { "uid": "105311152808", "nickname": "徐州烹鱼宴" },
    { "uid": "105631670886", "nickname": "皮卡丘开箱v" },
    { "uid": "111220453220", "nickname": "坤坤开箱评测"},
    { "uid": "105724975956", "nickname": "吴广妹子开箱"}
]